setup.py
src/fastai/__init__.py
src/fastai/_nbdev.py
src/fastai/_pytorch_doc.py
src/fastai/basics.py
src/fastai/collab.py
src/fastai/distributed.py
src/fastai/fp16_utils.py
src/fastai/imports.py
src/fastai/interpret.py
src/fastai/launch.py
src/fastai/layers.py
src/fastai/learner.py
src/fastai/losses.py
src/fastai/metrics.py
src/fastai/optimizer.py
src/fastai/test_utils.py
src/fastai/torch_basics.py
src/fastai/torch_core.py
src/fastai/torch_imports.py
src/fastai/callback/__init__.py
src/fastai/callback/all.py
src/fastai/callback/captum.py
src/fastai/callback/core.py
src/fastai/callback/cutmix.py
src/fastai/callback/data.py
src/fastai/callback/fp16.py
src/fastai/callback/hook.py
src/fastai/callback/mixup.py
src/fastai/callback/neptune.py
src/fastai/callback/preds.py
src/fastai/callback/progress.py
src/fastai/callback/rnn.py
src/fastai/callback/schedule.py
src/fastai/callback/tensorboard.py
src/fastai/callback/tracker.py
src/fastai/callback/training.py
src/fastai/callback/wandb.py
src/fastai/data/__init__.py
src/fastai/data/all.py
src/fastai/data/block.py
src/fastai/data/core.py
src/fastai/data/external.py
src/fastai/data/load.py
src/fastai/data/transforms.py
src/fastai/medical/__init__.py
src/fastai/medical/imaging.py
src/fastai/medical/text.py
src/fastai/tabular/__init__.py
src/fastai/tabular/all.py
src/fastai/tabular/core.py
src/fastai/tabular/data.py
src/fastai/tabular/learner.py
src/fastai/tabular/model.py
src/fastai/text/__init__.py
src/fastai/text/all.py
src/fastai/text/core.py
src/fastai/text/data.py
src/fastai/text/learner.py
src/fastai/text/models/__init__.py
src/fastai/text/models/awdlstm.py
src/fastai/text/models/core.py
src/fastai/text/models/qrnn.py
src/fastai/vision/__init__.py
src/fastai/vision/all.py
src/fastai/vision/augment.py
src/fastai/vision/core.py
src/fastai/vision/data.py
src/fastai/vision/gan.py
src/fastai/vision/learner.py
src/fastai/vision/utils.py
src/fastai/vision/widgets.py
src/fastai/vision/models/__init__.py
src/zwyfastai.egg-info/PKG-INFO
src/zwyfastai.egg-info/SOURCES.txt
src/zwyfastai.egg-info/dependency_links.txt
src/zwyfastai.egg-info/entry_points.txt
src/zwyfastai.egg-info/requires.txt
src/zwyfastai.egg-info/top_level.txt