Metadata-Version: 2.1
Name: zwyfastai
Version: 2.0.21
Summary: fastai simplifies training fast and accurate neural nets using modern best practices
Home-page: UNKNOWN
Author: Jeremy Howard, Sylvain Gugger, and contributors,zwy
Author-email: zuowangyang@foxmail.com
License: Apache Software License 2.0
Keywords: fastai,deep learning,machine,zwyfastai
Platform: any
Classifier: Development Status :: 5 - Production/Stable
Classifier: Intended Audience :: Developers
Classifier: License :: OSI Approved :: Apache Software License
Classifier: Natural Language :: English
Classifier: Programming Language :: Python :: 3.5
Classifier: Programming Language :: Python :: 3.6
Classifier: Programming Language :: Python :: 3.7
Classifier: Programming Language :: Python :: 3.8
Provides-Extra: dev
